textshape
