Metadata-Version: 2.4
Name: textshape
Version: 1.0.0.post1
Summary: Hyper fast hyphenation for Python
Author-email: Laurens Janssen <digi-deity@laurens.xyz>
License: Apache-2.0
Project-URL: Repository, https://github.com/digi-deity/textshape
Requires-Python: >=3.10
License-File: LICENSE
Requires-Dist: numpy>=2.0.0
Requires-Dist: vharfbuzz>=0.3.1
Requires-Dist: fonttools
Dynamic: license-file
